django_amazon_translate/__init__.py
django_amazon_translate/apps.py
django_amazon_translate/models.py
django_amazon_translate/translator.py
django_amazon_translate/management/__init__.py
django_amazon_translate/management/commands/__init__.py
django_amazon_translate/management/commands/auto_translate_text.py
django_amazon_translate/tests/__init__.py
django_amazon_translate/tests/test_auto_translate.py
django_amazon_translate/tests/test_translator.py
django_amazon_translate/tests/testapp/__init__.py
django_amazon_translate/tests/testapp/admin.py
django_amazon_translate/tests/testapp/models.py
django_amazon_translate/tests/testapp/translation.py
django_amazon_translate/tests/testapp/urls.py
django_amazon_translate-0.1.1.dist-info/LICENSE
django_amazon_translate-0.1.1.dist-info/METADATA
django_amazon_translate-0.1.1.dist-info/WHEEL
django_amazon_translate-0.1.1.dist-info/top_level.txt
django_amazon_translate-0.1.1.dist-info/RECORD
