Metadata-Version: 2.1
Name: django-amazon-translate
Version: 0.1.1
Summary: Utils for Django to translate both Models and Django gettext files using Amazon Translate.
Home-page: https://github.com/leepa/django_amazon_translate
Author: Lee Packham
Author-email: leepac@amazon.co.uk
License: MIT license
Keywords: django_amazon_translate
Platform: UNKNOWN
Classifier: Development Status :: 2 - Pre-Alpha
Classifier: Intended Audience :: Developers
Classifier: License :: OSI Approved :: MIT License
Classifier: Natural Language :: English
Classifier: Programming Language :: Python :: 3
Classifier: Programming Language :: Python :: 3.4
Classifier: Programming Language :: Python :: 3.5
Classifier: Programming Language :: Python :: 3.6
Classifier: Programming Language :: Python :: 3.7
Classifier: Programming Language :: Python :: 3.8
Requires-Dist: django (>=1.11)
Requires-Dist: django-modeltranslation (<1.0,>=0.13.1)
Requires-Dist: boto3 (<=1.13,>=1.9)
Requires-Dist: polib (<2,>=1.1.0)
